dbcli/__init__.py
dbcli/mcli.py
dbcli/rcli.py
dbcli/test_mcli.py
dbcli/test_rcli.py
dbcli_mongo_redis-0.3.7.dist-info/METADATA
dbcli_mongo_redis-0.3.7.dist-info/WHEEL
dbcli_mongo_redis-0.3.7.dist-info/entry_points.txt
dbcli_mongo_redis-0.3.7.dist-info/top_level.txt
dbcli_mongo_redis-0.3.7.dist-info/RECORD
