Metadata-Version: 2.1
Name: dbcli-mongo-redis
Version: 0.3.7
Summary: Mongo and redis cli
Home-page: https://github.com/orasul/dbcli
Author: Rasul Osmanov
License: UNKNOWN
Platform: UNKNOWN
Requires-Dist: click
Requires-Dist: flatten-json
Requires-Dist: pymongo
Requires-Dist: redis
